redditor/__init__.py
redditor/main.py
redditor-0.2.dist-info/LICENSE
redditor-0.2.dist-info/METADATA
redditor-0.2.dist-info/WHEEL
redditor-0.2.dist-info/entry_points.txt
redditor-0.2.dist-info/top_level.txt
redditor-0.2.dist-info/RECORD
