Metadata-Version: 2.1
Name: redditor
Version: 0.2
Summary: use reddit like a doge
Home-page: https://github.com/daenylio/redditor
Author: Tuan Nguyen
Author-email: tuan.nguyenviet271@gmail.com
License: UNKNOWN
Platform: UNKNOWN
Classifier: Programming Language :: Python :: 3
Classifier: License :: OSI Approved :: MIT License
Classifier: Operating System :: OS Independent
Requires-Dist: click
Requires-Dist: praw
